helixswarm/__init__.py
helixswarm/exceptions.py
helixswarm/helpers.py
helixswarm/py.typed
helixswarm/swarm.py
helixswarm/adapters/__init__.py
helixswarm/adapters/aio.py
helixswarm/adapters/sync.py
helixswarm/endpoints/__init__.py
helixswarm/endpoints/activities.py
helixswarm/endpoints/changes.py
helixswarm/endpoints/comments.py
helixswarm/endpoints/groups.py
helixswarm/endpoints/projects.py
helixswarm/endpoints/reviews.py
helixswarm/endpoints/servers.py
helixswarm/endpoints/users.py
helixswarm/endpoints/workflows.py
tests/__init__.py
tests/conftest.py
tests/test_activities.py
tests/test_changes.py
tests/test_comments.py
tests/test_groups.py
tests/test_projects.py
tests/test_reviews.py
tests/test_servers.py
tests/test_swarm.py
tests/test_users.py
tests/test_workflows.py
helix_swarm-0.7.4.dist-info/LICENSE
helix_swarm-0.7.4.dist-info/METADATA
helix_swarm-0.7.4.dist-info/WHEEL
helix_swarm-0.7.4.dist-info/top_level.txt
helix_swarm-0.7.4.dist-info/RECORD
