Metadata-Version: 2.1
Name: helix-swarm
Version: 0.7.4
Summary: Python client for Perforce Helix Swarm (review board)
Home-page: https://github.com/pbelskiy/helix-swarm
Download-URL: https://pypi.org/project/helix-swarm
Author: Petr Belskiy
License: MIT
Keywords: helix,swarm,swarm review,perforce helix swarm
Classifier: Programming Language :: Python
Classifier: Programming Language :: Python :: 3
Classifier: Programming Language :: Python :: 3.7
Classifier: Programming Language :: Python :: 3.8
Classifier: Programming Language :: Python :: 3.9
Classifier: Programming Language :: Python :: 3.10
Classifier: Programming Language :: Python :: 3.11
Requires-Python: >=3.7
License-File: LICENSE
Requires-Dist: aiohttp (<4.0.0,>3.6.2)
Requires-Dist: requests (<3.0.0,>=2.24.0)
